[
    {
        "_id": "1",
        "courseName": "Introduction to Java as a Second Language",
        "rating": "5",
        "teacher": "by Adrian Dawson school",
        "duration": "48 lectures ( 280 Hours)",
        "courseFee": "$120 all course / $20 per month",
        "motive": ""
    },
    {
        "_id": "2",
        "courseName": "Object Oriented Programming in Java. First step",
        "rating": "5",
        "teacher": "by Adrian Dawson school",
        "duration": "48 lectures ( 280 Hours)",
        "courseFee": "$120 all course / $20 per month",
        "motive": ""
    },
    {
        "_id": "3",
        "courseName": "HTML, CSS, and Javascript for Web Developers",
        "rating": "5",
        "teacher": "by Adrian Dawson school",
        "duration": "48 lectures ( 280 Hours)",
        "courseFee": "$120 all course / $20 per month",
        "motive": ""
    },
    {
        "_id": "4",
        "courseName": "Introduction to Programming with Python",
        "rating": "5",
        "teacher": "by Adrian Dawson school",
        "duration": "48 lectures ( 280 Hours)",
        "courseFee": "$120 all course / $20 per month",
        "motive": ""
    },
    {
        "_id": "5",
        "courseName": "Fundamental blockchain technology",
        "rating": "5",
        "teacher": "by Adrian Dawson school",
        "duration": "48 lectures ( 280 Hours)",
        "courseFee": "$120 all course / $20 per month",
        "motive": ""
    },
    {
        "_id": "6",
        "courseName": "Responsive Website : Code with HTML, CSS, JS",
        "rating": "5",
        "teacher": "by Adrian Dawson school",
        "duration": "48 lectures ( 280 Hours)",
        "courseFee": "$120 all course / $20 per month",
        "motive": ""
    },
    {
        "_id": "7",
        "courseName": "Advanced Statistics for Data Science and Programming",
        "rating": "5",
        "teacher": "by Adrian Dawson school",
        "duration": "48 lectures ( 280 Hours)",
        "courseFee": "$120 all course / $20 per month",
        "motive": ""
    },
    {
        "_id": "8",
        "courseName": "Computer Programming Basic",
        "rating": "5",
        "teacher": "by Adrian Dawson school",
        "duration": "48 lectures ( 280 Hours)",
        "courseFee": "$120 all course / $20 per month",
        "motive": ""
    },
    {
        "_id": "9",
        "courseName": "ComputerCSS3 Programming",
        "rating": "5",
        "teacher": "by Adrian Dawson school",
        "duration": "48 lectures ( 280 Hours)",
        "courseFee": "$120 all course / $20 per month",
        "motive": ""
    },
    {
        "_id": "10",
        "courseName": "Web-site Development Pro",
        "rating": "5",
        "teacher": "by Adrian Dawson school",
        "duration": "48 lectures ( 280 Hours)",
        "courseFee": "$120 all course / $20 per month",
        "motive": ""
    },
    {
        "_id": "11",
        "courseName": "Software Engineering Fundamentals",
        "rating": "5",
        "teacher": "by Adrian Dawson school",
        "duration": "48 lectures ( 280 Hours)",
        "courseFee": "$120 all course / $20 per month",
        "motive": ""
    }
]